{"expireTime":9007200961342055000,"key":"ad338fa84a21b4c4d5c2c0067a9d3b0a","val":{"name":"IMAGE_PROCESSING","inputPaths":["C:/Users/vikra/Desktop/My-Portfolio/src/static/images/hfest_avatar_2.jpg"],"outputDir":"C:/Users/vikra/Desktop/My-Portfolio/public/static/697ce0e9b60cda91eee64f18fc00f81b","args":{"isLazy":false,"operations":[{"outputPath":"0a9c8\\hfest_avatar_2.jpg","args":{"width":500,"cropFocus":17,"toFormat":"jpg","quality":90,"fit":"cover","background":"rgba(0,0,0,1)"}}],"pluginOptions":{"base64Width":20,"forceBase64Format":"","useMozJpeg":false,"stripMetadata":true,"lazyImageGeneration":true,"defaultQuality":50,"failOnError":true,"plugins":[]}}}}